{
    "works": {
        "work":[
            {
                "name": "M&C Saatchi",
                "id": "M&CSaatchi",
                "img": "http://pollenlondon.com/wp-content/uploads/2014/01/MC-Saatchi-1940x1304.jpg",
                "thumbnail": "http://pollenlondon.com/wp-content/uploads/2014/01/MC-Saatchi21-1293x710.jpg",
                "description": "Creating a Digital Presence for an Interactive Sports Agency",
                "breif": "Designed and developed a portfolio site for M&C Saatchi Sport &amp; Entertainment, showcasing their clients and case studies.",
                "type": "Web/Design"
            },
            {
                "name": "The Last of Us",
                "id": "lastofus",
                "img": "http://www.thelastofus.playstation.com/img/media-2.jpg",
                "thumbnail": "http://payload249.cargocollective.com/1/1/51400/7288975/TLOU_MainSite-Home_Devices2_960.jpg",
                "description": "Designing the Website for an Intense Story-Driven Thriller Game. Rated 10/10 by IGN",
                "breif": "Developed the main website for critically acclaimed action game, <i>The Last Of Us</i>, depicting its highly detailed imagery and intense story.",
                "type": "Web/Design"
            },
            {
                "name": "Star Trek: Into the Darkness",
                "id": "StarTrek",
                "img": "http://payload239.cargocollective.com/1/1/51400/7092297/ST_Art05_o.jpg",
                "thumbnail": "http://payload239.cargocollective.com/1/1/51400/7092297/ST_Art06_960.jpg",
                "description": "Animation Work for the Sequel to the Star Trek Movie Franchise",
                "breif": "Animated and designed an advertisment poster for promotions of the film, <i>Star Trek: Into the Darkness</i>.",
                "type": "Animation/Design"
            },
            {
                "name": "X-Men: Days of Future Past - Track Industries",
                "id": "xmen-dofp-trackindusties",
                "img": "http://payload249.cargocollective.com/1/1/51400/7288971/TraskPortrait2_o.jpg",
                "thumbnail": "http://payload249.cargocollective.com/1/1/51400/7288971/Trask_Devices01_960.jpg",
                "description": "Interactive Website Introducing Track Industries from the X-Men Series",
                "breif": "Designed the website introducing Track Industries, a core component of the X-Men series, to promote the film, <i>X-Men: Days of Future's Past</i>.",
                "type": "Web/Design/UI/UX"
            }
        ]
    }
}